[
  {
    "id": 1747299470127,
    "type": "planifeo",
    "position": 0,
    "date": "2025-05-09T08:57:50.127Z"
  },
  {
    "id": 1747299472624,
    "type": "planifeo",
    "position": 1,
    "date": "2025-05-10T08:57:52.624Z"
  },
  {
    "id": 1747299474150,
    "type": "planifeo",
    "position": 2,
    "date": "2025-05-12T08:57:54.150Z"
  },
  {
    "id": 1747299475578,
    "type": "planifeo",
    "position": 3,
    "date": "2025-05-13T08:57:55.578Z"
  },
  {
    "id": 1747299476468,
    "type": "planifeo",
    "position": 4,
    "date": "2025-05-14T08:57:56.468Z"
  },
  {
    "id": 1747299477032,
    "type": "planifeo",
    "position": 5,
    "date": "2025-05-14T08:57:57.032Z"
  },
  {
    "id": 1747299478927,
    "type": "planifeo",
    "position": 6,
    "date": "2025-05-15T08:57:58.927Z"
  },
  {
    "id": 1747299479830,
    "type": "planifeo",
    "position": 7,
    "date": "2025-05-15T08:57:59.830Z"
  }
]